{
  "users": [
    {
      "username": "hwretham0",
      "password": "iM7_oDoa9FW5Oh",
      "balance": 1055
    },
    {
      "username": "mmacdearmaid1",
      "password": "gQ5<+,b#?",
      "balance": 14676
    },
    {
      "username": "acastellani2",
      "password": "bS0|<hK@1bhew",
      "balance": 10128
    },
    {
      "username": "aneesham3",
      "password": "zU9&a3IV",
      "balance": 11693
    },
    {
      "username": "scolleymore4",
      "password": "zP0(FQ&J{Ng.tz",
      "balance": 8735
    },
    {
      "username": "drivard5",
      "password": "dR8%&,XQeVT\"&o",
      "balance": 3944
    },
    {
      "username": "rmuffen6",
      "password": "iC7|#Se+8mD",
      "balance": 13569
    },
    {
      "username": "cborgnol7",
      "password": "tR9)>*s.WS%p%",
      "balance": 13077
    },
    {
      "username": "bcolum8",
      "password": "nJ8{5NL1R",
      "balance": 10028
    },
    {
      "username": "tprosch9",
      "password": "cE8??O{0",
      "balance": 14569
    },
    {
      "username": "rboomea",
      "password": "eV0?_gp.+JEz",
      "balance": 702
    },
    {
      "username": "kbakhrushkinb",
      "password": "cU6|S0ob#",
      "balance": 66
    },
    {
      "username": "mbeckinghamc",
      "password": "uO2/qA{Q<@%",
      "balance": 4351
    },
    {
      "username": "eginied",
      "password": "hV3\\j{*NJWQ\\Sk",
      "balance": 1906
    },
    {
      "username": "lgrealishe",
      "password": "wO2/gRoSdQ",
      "balance": 5622
    },
    {
      "username": "asellensf",
      "password": "lP2.&6=0",
      "balance": 9438
    },
    {
      "username": "djeandelg",
      "password": "mI9?QV8&{Qy5",
      "balance": 4394
    },
    {
      "username": "akalkerh",
      "password": "qB9\"R\"M+@KvTB",
      "balance": 571
    },
    {
      "username": "flearoydei",
      "password": "pA2._+oMQr`\\~Q=",
      "balance": 1901
    },
    {
      "username": "phurleyj",
      "password": "bJ8_(9MGi$r",
      "balance": 11835
    },
    {
      "username": "dcuttlesk",
      "password": "zL0@+L8}",
      "balance": 6480
    },
    {
      "username": "bsouthalll",
      "password": "lK2(w{DLZeHoG",
      "balance": 9103
    },
    {
      "username": "yoshirinem",
      "password": "rJ1{G3\"XL.Y!?mj",
      "balance": 2274
    },
    {
      "username": "dchicchellin",
      "password": "nJ4!gL~*",
      "balance": 7058
    },
    {
      "username": "shuglando",
      "password": "lY8)B_XV&srm~Q\"<",
      "balance": 6626
    }
  ]
}